JsonDatabaseZ/__init__.py
JsonDatabaseZ/database.py
JsonDatabaseZ-0.0.2.dist-info/METADATA
JsonDatabaseZ-0.0.2.dist-info/WHEEL
JsonDatabaseZ-0.0.2.dist-info/top_level.txt
JsonDatabaseZ-0.0.2.dist-info/RECORD
