Metadata-Version: 2.1
Name: JsonDatabaseZ
Version: 0.0.2
Home-page: https://github.com/ReyDev2009
Author: Rey Michel Del Toro Martinez
Author-email: martinez200921@gmail.com
License: MIT
